iban_oplata/__init__.py
iban_oplata/client.py
iban_oplata/enum.py
iban_oplata/exceptions.py
iban_oplata/response.py
iban_oplata/typed_dict.py
iban_oplata-0.0.2.dist-info/licenses/LICENSE
iban_oplata-0.0.2.dist-info/METADATA
iban_oplata-0.0.2.dist-info/WHEEL
iban_oplata-0.0.2.dist-info/top_level.txt
iban_oplata-0.0.2.dist-info/RECORD
