Metadata-Version: 2.4
Name: iban-oplata
Version: 0.0.2
Summary: Python SDK for ibanoplata.com API
Maintainer-email: Dmytro Litvinov <me@dmytrolitvinov.com>
License: MIT License
Project-URL: Homepage, https://github.com/DmytroLitvinov/python-iban-oplata
Project-URL: Issues, https://github.com/DmytroLitvinov/python-iban-oplata/issues
Project-URL: Changelog, https://github.com/DmytroLitvinov/python-iban-oplata/blob/main/CHANGELOG.md
Keywords: iban,iban oplata,Ukraine,🇺🇦,api,ibanoplata.com
Classifier: Development Status :: 4 - Beta
Classifier: Environment :: Web Environment
Classifier: Intended Audience :: Developers
Classifier: License :: OSI Approved :: MIT License
Classifier: Natural Language :: English
Classifier: Operating System :: OS Independent
Classifier: Programming Language :: Python
Classifier: Programming Language :: Python :: 3
Classifier: Programming Language :: Python :: 3.8
Classifier: Programming Language :: Python :: 3.9
Classifier: Programming Language :: Python :: 3.10
Classifier: Programming Language :: Python :: 3.11
Classifier: Programming Language :: Python :: 3.12
Classifier: Programming Language :: Python :: 3.13
Classifier: Topic :: Internet :: WWW/HTTP
Classifier: Topic :: Software Development :: Libraries :: Python Modules
Requires-Python: >=3.8
License-File: LICENSE
Requires-Dist: requests
Dynamic: license-file
